py_calculator/__init__.py
py_calculator/calc.py
py_calculator/hellosz.py
py_expression_calculator_ltcsz-1.0.0.dist-info/METADATA
py_expression_calculator_ltcsz-1.0.0.dist-info/WHEEL
py_expression_calculator_ltcsz-1.0.0.dist-info/top_level.txt
py_expression_calculator_ltcsz-1.0.0.dist-info/RECORD
