Metadata-Version: 2.4
Name: py-expression-calculator-ltcsz
Version: 1.0.0
Summary: A simple expression calculator that supports +, -, *, / operators.
Author-email: Your Name <your.email@example.com>
Project-URL: Homepage, https://github.com/your-username/your-repo-name
Project-URL: Bug Tracker, https://github.com/your-username/your-repo-name/issues
Classifier: Programming Language :: Python :: 3
Classifier: License :: OSI Approved :: MIT License
Classifier: Operating System :: OS Independent
Requires-Python: >=3.8
